prespy/__about__.py
prespy/__init__.py
prespy/__main__.py
prespy/exceptions.py
prespy/logfile.py
prespy/mri.py
prespy/scla.py
prespy/sndan.py
prespy/scla/__init__.py
prespy/scla/runall.py
prespy/scla/setupscla.py
prespy/scla/sndan.py
prespy-0.0.12.dist-info/DESCRIPTION.rst
prespy-0.0.12.dist-info/METADATA
prespy-0.0.12.dist-info/RECORD
prespy-0.0.12.dist-info/WHEEL
prespy-0.0.12.dist-info/entry_points.txt
prespy-0.0.12.dist-info/metadata.json
prespy-0.0.12.dist-info/top_level.txt
