Metadata-Version: 1.1
Name: prespy
Version: 0.0.12
Summary: Package for working with the Neurobehavioural Systems Presentation logfiles within python
Home-page: https://github.com/gjcooper/prespy
Author: Gavin Cooper
Author-email: gjcooper@gmail.com
License: GPLv2
Keywords: Presentation,NBS,logfile
Platform: UNKNOWN
Classifier: Development Status :: 3 - Alpha
Classifier: Intended Audience :: Developers
Classifier: Programming Language :: Python :: 3
